.gitignore
LICENSE
MANIFEST.in
NOTICES
README.rst
setup.py
loomengine_worker/.gitignore
loomengine_worker/VERSION
loomengine_worker/__init__.py
loomengine_worker/inputs.py
loomengine_worker/outputs.py
loomengine_worker/parsers.py
loomengine_worker/task_monitor.py
loomengine_worker.egg-info/PKG-INFO
loomengine_worker.egg-info/SOURCES.txt
loomengine_worker.egg-info/dependency_links.txt
loomengine_worker.egg-info/entry_points.txt
loomengine_worker.egg-info/requires.txt
loomengine_worker.egg-info/top_level.txt
loomengine_worker/test/all_types_inputs_outputs.yaml
loomengine_worker/test/test_task_monitor.py